mojo/factories/testplusfactory.py
mojo/testplus/__init__.py
mojo/testplus/cli/__init__.py
mojo/testplus/cli/cmdtree/__init__.py
mojo/testplus/cli/cmdtree/testing/__init__.py
mojo/testplus/cli/cmdtree/testing/constants.py
mojo/testplus/cli/cmdtree/testing/jobs.py
mojo/testplus/cli/cmdtree/testing/query.py
mojo/testplus/cli/cmdtree/testing/run.py
mojo/testplus/cli/cmdtree/utilities/__init__.py
mojo/testplus/cli/cmdtree/utilities/timestamp.py
mojo/testplus/cli/testplus_command.py
mojo/testplus/diagnostics.py
mojo/testplus/entrypoints.py
mojo/testplus/exceptions.py
mojo/testplus/expressions.py
mojo/testplus/extensionprotocols.py
mojo/testplus/initialize.py
mojo/testplus/queries.py
mojo/testplus/reflection.py
mojo/testplus/resultserver.py
mojo/testplus/sequencing/__init__.py
mojo/testplus/sequencing/sequencermodulescope.py
mojo/testplus/sequencing/sequencerscopebase.py
mojo/testplus/sequencing/sequencersessionscope.py
mojo/testplus/sequencing/sequencertestscope.py
mojo/testplus/sequencing/testactivity.py
mojo/testplus/sequencing/testsequencer.py
mojo/testplus/templates/__init__.py
mojo/testplus/templates/v0/static/prism.css
mojo/testplus/templates/v0/static/prism.js
mojo/testplus/templates/v0/static/test-report-banner-background-image.png
mojo/testplus/templates/v0/static/testsummary.css
mojo/testplus/templates/v0/static/testsummary.js
mojo/testplus/templates/v0/static/w3.css
mojo/testplus/templates/v0/tabs/tab-images.html
mojo/testplus/templates/v0/tabs/tab-sounds.html
mojo/testplus/templates/v0/testsummary.html
mojo/testplus/templates/v1/static/prism.css
mojo/testplus/templates/v1/static/prism.js
mojo/testplus/templates/v1/static/test-report-banner-background-image.png
mojo/testplus/templates/v1/static/testhelpers.js
mojo/testplus/templates/v1/static/testsummary.css
mojo/testplus/templates/v1/static/testsummary.js
mojo/testplus/templates/v1/static/w3.css
mojo/testplus/templates/v1/tabs/tab-images.html
mojo/testplus/templates/v1/tabs/tab-sounds.html
mojo_testplus-2.0.7.dist-info/LICENSE.txt
mojo_testplus-2.0.7.dist-info/METADATA
mojo_testplus-2.0.7.dist-info/WHEEL
mojo_testplus-2.0.7.dist-info/entry_points.txt
mojo_testplus-2.0.7.dist-info/RECORD
