Metadata-Version: 2.1
Name: mojo-testplus
Version: 2.0.7
Summary: Automation Mojo TestPlus Test Framework
Home-page: http://automationmojo.com
License: LICENSE.txt
Keywords: python
Author: Myron Walker
Author-email: myron.walker@gmail.com
Requires-Python: >=3.9,<4.0
Classifier: License :: OSI Approved :: MIT License
Classifier: License :: Other/Proprietary License
Classifier: Operating System :: POSIX
Classifier: Programming Language :: Python :: 3
Classifier: Programming Language :: Python :: 3.9
Classifier: Programming Language :: Python :: 3.10
Classifier: Programming Language :: Python :: 3.11
Classifier: Programming Language :: Python :: 3.12
Requires-Dist: click (>=8.1.3,<9.0.0)
Requires-Dist: debugpy (>=1.6.5,<2.0.0)
Requires-Dist: mojo-collections (>=2.0.0,<2.1.0)
Requires-Dist: mojo-config (>=2.0.0,<2.1.0)
Requires-Dist: mojo-errors (>=2.0.1,<2.1.0)
Requires-Dist: mojo-extension (>=2.0.0,<2.1.0)
Requires-Dist: mojo-results (>=2.0.0,<2.1.0)
Requires-Dist: mojo-runtime (>=2.0.0,<2.1.0)
Requires-Dist: mojo-xmodules (>=2.0.0,<2.1.0)
Requires-Dist: requests (>=2.32.3,<3.0.0)
Project-URL: Repository, https://github.com/automationmojo/testplus
